README.rst
setup.py
sqlitis/__init__.py
sqlitis/cli.py
sqlitis/convert.py
sqlitis/models.py
sqlitis.egg-info/PKG-INFO
sqlitis.egg-info/SOURCES.txt
sqlitis.egg-info/dependency_links.txt
sqlitis.egg-info/entry_points.txt
sqlitis.egg-info/requires.txt
sqlitis.egg-info/top_level.txt