Metadata-Version: 1.1
Name: sqlitis
Version: 0.0.2
Summary: convert sql to sqlalchemy expressions
Home-page: https://github.com/pglass/sqlitis
Author: Paul Glass
Author-email: pnglass@gmail.com
License: MIT
Keywords: sql sqlalchemy convert sqlitis
Platform: UNKNOWN
Classifier: Development Status :: 2 - Pre-Alpha
Classifier: Environment :: Console
Classifier: Intended Audience :: Developers
Classifier: License :: OSI Approved :: MIT License
Classifier: Operating System :: OS Independent
Classifier: Programming Language :: Python :: 2.7
Classifier: Programming Language :: Python :: 3.5
Classifier: Programming Language :: Python :: 3.6
